zip_fit/__init__.py
zip_fit/zipfit.py
zip_fit-1.0.9.dist-info/LICENSE
zip_fit-1.0.9.dist-info/METADATA
zip_fit-1.0.9.dist-info/WHEEL
zip_fit-1.0.9.dist-info/top_level.txt
zip_fit-1.0.9.dist-info/RECORD
