Metadata-Version: 2.1
Name: zip-fit
Version: 1.0.9
Summary: Data Selection via Compression-Based Alignment
Author: Elyas Obbad
Author-email: Elyas Obbad <eobbad@stanford.edu>
License: 
Keywords: data selection,compression,zip-fit,nlp,language models
Classifier: Programming Language :: Python :: 3
Classifier: License :: OSI Approved :: MIT License
Classifier: Operating System :: OS Independent
Requires-Python: >=3.6
License-File: LICENSE
Requires-Dist: numpy>=1.21.0
Requires-Dist: lz4>=3.1.10
Requires-Dist: datasets>=1.17.0
Provides-Extra: dev
Requires-Dist: pytest>=6.0; extra == "dev"
Requires-Dist: flake8>=3.9; extra == "dev"
Requires-Dist: black>=21.0; extra == "dev"
Requires-Dist: mypy>=0.910; extra == "dev"
